obstechutils/__init__.py
obstechutils/array.py
obstechutils/connection.py
obstechutils/coordinates.py
obstechutils/credentials.py
obstechutils/dataclasses.py
obstechutils/email.py
obstechutils/exceptions.py
obstechutils/google.py
obstechutils/inventory.py
obstechutils/logging.py
obstechutils/precise_timing.py
obstechutils/regression.py
obstechutils/rinex.py
obstechutils/roof.py
obstechutils/stats.py
obstechutils/telegram.py
obstechutils/types.py
obstechutils/argparse/__init__.py
obstechutils/argparse/configparse.py
obstechutils/argparse/mqttparse.py
obstechutils/cameras/__init__.py
obstechutils/cameras/asi.py
obstechutils/cameras/base.py
obstechutils/cameras/cdlltools.py
obstechutils/db/__init__.py
obstechutils/db/database.py
obstechutils/db/weatherupdate.py
obstechutils/meteo/__init__.py
obstechutils/meteo/dimm.py
obstechutils/meteo/functions.py
obstechutils/mqtt/__init__.py
obstechutils/mqtt/client.py
obstechutils/scripts/__init__.py
obstechutils/scripts/device_status.py
obstechutils/scripts/list_roofs.py
obstechutils/scripts/mix_weather_sensors.py
obstechutils/scripts/monitor_weather_sensor.py
obstechutils/scripts/mqtt_console.py
obstechutils/scripts/update_sql_table.py
obstechutils/sensors/__init__.py
obstechutils/sensors/aag.py
obstechutils/sensors/fuser.py
obstechutils/sensors/meteosensor.py
obstechutils/sensors/mixer.py
obstechutils/sensors/nm150.py
obstechutils/sensors/pyrgeometer.py
obstechutils-0.2.3.dist-info/METADATA
obstechutils-0.2.3.dist-info/WHEEL
obstechutils-0.2.3.dist-info/entry_points.txt
obstechutils-0.2.3.dist-info/top_level.txt
obstechutils-0.2.3.dist-info/RECORD
