Metadata-Version: 2.1
Name: obstechutils
Version: 0.2.3
Summary: Utilities for obstech
Author-email: Régis Lachaume <regis.lachaume@gmail.com>
Classifier: Programming Language :: Python :: 3
Classifier: Development Status :: 4 - Beta
Classifier: Intended Audience :: Science/Research
Classifier: Operating System :: Microsoft :: Windows
Classifier: Operating System :: POSIX
Classifier: Topic :: Scientific/Engineering :: Astronomy
Requires-Python: >=3.9
Requires-Dist: pydantic[email]
Requires-Dist: mysql-connector-python
Requires-Dist: pyYAML
Requires-Dist: paho-mqtt
Requires-Dist: astropy
Requires-Dist: google-spreadsheet
Requires-Dist: google-auth-oauthlib
Requires-Dist: html2text
Requires-Dist: pyserial
Requires-Dist: numpy
Requires-Dist: scipy
Requires-Dist: photutils
Requires-Dist: opencv-python
Requires-Dist: zwoasi
Requires-Dist: mpmath
Requires-Dist: pynmea2
Requires-Dist: eval-type-backport ; python_version < "3.10"
